tsbook/datasets/retail.py
tsbook/datasets/simple.py
tsbook/forecasting/reduction.py
tsbook-0.1.0.dist-info/LICENSE
tsbook-0.1.0.dist-info/METADATA
tsbook-0.1.0.dist-info/WHEEL
tsbook-0.1.0.dist-info/RECORD
