Metadata-Version: 2.1
Name: tsbook
Version: 0.1.0
Summary: 
License: Apache-2.0
Author: felipeangelimvieira
Author-email: felipeangelim@gmail.com
Requires-Python: >=3.11,<3.14
Classifier: License :: OSI Approved :: Apache Software License
Classifier: Programming Language :: Python :: 3
Classifier: Programming Language :: Python :: 3.11
Classifier: Programming Language :: Python :: 3.12
Classifier: Programming Language :: Python :: 3.13
Requires-Dist: jupyter (>=1.1.1,<2.0.0)
Requires-Dist: lightgbm (>=4.6.0,<5.0.0)
Requires-Dist: matplotlib (>=3.10.7,<4.0.0)
Requires-Dist: prophetverse (>=0.10.0,<0.11.0) ; python_version >= "3.9" and python_version < "3.12"
Requires-Dist: pytorch-forecasting (>=1.5.0,<2.0.0)
Requires-Dist: scikit-learn (>=1.7.2,<2.0.0)
Requires-Dist: seaborn (>=0.13.2,<0.14.0)
Requires-Dist: sktime (>=0.39.0,<0.40.0)
Requires-Dist: statsmodels (>=0.14.5,<0.15.0)
